LICENCE.txt
MANIFEST.in
README
setup.cfg
setup.py
emencia_yuic.egg-info/PKG-INFO
emencia_yuic.egg-info/SOURCES.txt
emencia_yuic.egg-info/dependency_links.txt
emencia_yuic.egg-info/entry_points.txt
emencia_yuic.egg-info/not-zip-safe
emencia_yuic.egg-info/requires.txt
emencia_yuic.egg-info/top_level.txt
yuicompressor/__init__.py
yuicompressor/yuicompressor-2.4.8.jar